README.md
setup.py
l2metrics/__init__.py
l2metrics/__main__.py
l2metrics/__version__.py
l2metrics/_localutil.py
l2metrics/average_performance.py
l2metrics/block_saturation.py
l2metrics/clear_ste.py
l2metrics/core.py
l2metrics/metrics_parser.py
l2metrics/normalizer.py
l2metrics/parser.py
l2metrics/performance_maintenance.py
l2metrics/performance_recovery.py
l2metrics/plot.py
l2metrics/recovery_time.py
l2metrics/report.py
l2metrics/sample_efficiency.py
l2metrics/ste_relative_performance.py
l2metrics/terminal_performance.py
l2metrics/transfer.py
l2metrics/util.py
l2metrics.egg-info/PKG-INFO
l2metrics.egg-info/SOURCES.txt
l2metrics.egg-info/dependency_links.txt
l2metrics.egg-info/requires.txt
l2metrics.egg-info/top_level.txt
tests/__init__.py
tests/test_metrics.py
tests/test_metrics_report.py
tests/test_preprocessing.py