Metadata-Version: 2.1
Name: l2metrics
Version: 3.1.0
Summary: Metrics for Lifelong Learning
Home-page: https://github.com/lifelong-learning-systems/l2metrics
Author: Eric Nguyen, Megan Baker
Author-email: Eric.Nguyen@jhuapl.edu, Megan.Baker@jhuapl.edu
License: MIT
Download-URL: https://github.com/lifelong-learning-systems/l2metrics/archive/v3.1.0.tar.gz
Platform: UNKNOWN
Classifier: Development Status :: 5 - Production/Stable
Classifier: License :: OSI Approved :: MIT License
Classifier: Programming Language :: Python :: 3
Classifier: Programming Language :: Python :: 3.7
Classifier: Programming Language :: Python :: 3.8
Classifier: Programming Language :: Python :: 3.9
Classifier: Topic :: Scientific/Engineering :: Artificial Intelligence
Requires-Python: >=3.7
